amazon_invoice_downloader/__about__.py
amazon_invoice_downloader/__init__.py
amazon_invoice_downloader/__main__.py
amazon_invoice_downloader/cli/__init__.py
amazon_invoice_downloader-0.4.0.dist-info/METADATA
amazon_invoice_downloader-0.4.0.dist-info/WHEEL
amazon_invoice_downloader-0.4.0.dist-info/entry_points.txt
amazon_invoice_downloader-0.4.0.dist-info/licenses/LICENSE.txt
amazon_invoice_downloader-0.4.0.dist-info/RECORD
