Metadata-Version: 2.1
Name: amazon-invoice-downloader
Version: 0.4.0
Summary: Logs into an Amazon.com account and downloads invoices as PDF
Project-URL: Documentation, https://github.com/dcwangmit01/amazon-invoice-downloader#readme
Project-URL: Issues, https://github.com/dcwangmit01/amazon-invoice-downloader/issues
Project-URL: Source, https://github.com/dcwangmit01/amazon-invoice-downloader
Author-email: David C Wang <dcwangmit01@gmail.com>
License-Expression: MIT
License-File: LICENSE.txt
Keywords: amazon,download,invoice,pdf,statements
Classifier: Development Status :: 4 - Beta
Classifier: Programming Language :: Python
Classifier: Programming Language :: Python :: 3.7
Classifier: Programming Language :: Python :: 3.8
Classifier: Programming Language :: Python :: 3.9
Classifier: Programming Language :: Python :: 3.10
Classifier: Programming Language :: Python :: 3.11
Classifier: Programming Language :: Python :: Implementation :: CPython
Classifier: Programming Language :: Python :: Implementation :: PyPy
Requires-Python: >=3.7
Requires-Dist: docopt~=0.6.2
Requires-Dist: playwright~=1.36.0
